django_le_social-0.9.dist-info/DESCRIPTION.rst
django_le_social-0.9.dist-info/METADATA
django_le_social-0.9.dist-info/RECORD
django_le_social-0.9.dist-info/WHEEL
django_le_social-0.9.dist-info/metadata.json
django_le_social-0.9.dist-info/top_level.txt
le_social/__init__.py
le_social/test_settings.py
le_social/utils.py
le_social/openid/__init__.py
le_social/openid/forms.py
le_social/openid/middleware.py
le_social/openid/models.py
le_social/openid/store.py
le_social/openid/utils.py
le_social/openid/views.py
le_social/openid/test_templates/le_social/openid/openid.html
le_social/openid/tests/__init__.py
le_social/openid/tests/tests.py
le_social/openid/tests/urls.py
le_social/openid/tests/views.py
le_social/registration/__init__.py
le_social/registration/forms.py
le_social/registration/models.py
le_social/registration/views.py
le_social/registration/test_templates/le_social/registration/activate.html
le_social/registration/test_templates/le_social/registration/activation_complete.html
le_social/registration/test_templates/le_social/registration/activation_email.txt
le_social/registration/test_templates/le_social/registration/activation_email_subject.txt
le_social/registration/test_templates/le_social/registration/expired_activation_email.txt
le_social/registration/test_templates/le_social/registration/register.html
le_social/registration/test_templates/le_social/registration/registration_closed.html
le_social/registration/test_templates/le_social/registration/registration_complete.html
le_social/registration/tests/__init__.py
le_social/registration/tests/tests.py
le_social/registration/tests/urls.py
le_social/registration/tests/views.py
le_social/twitter/__init__.py
le_social/twitter/models.py
le_social/twitter/views.py
le_social/twitter/tests/__init__.py
le_social/twitter/tests/tests.py
le_social/twitter/tests/urls.py
le_social/twitter/tests/views.py
