Metadata-Version: 2.0
Name: django-le-social
Version: 0.9
Summary: External registration / authentication for Django
Home-page: https://github.com/brutasse/django-le-social
Author: Bruno Renié
Author-email: bruno@renie.fr
License: BSD licence, see LICENCE file
Platform: UNKNOWN
Classifier: Development Status :: 3 - Alpha
Classifier: Environment :: Web Environment
Classifier: Framework :: Django
Classifier: Intended Audience :: Developers
Classifier: License :: OSI Approved :: BSD License
Classifier: Natural Language :: English
Classifier: Programming Language :: Python
Classifier: Programming Language :: Python :: 3
Requires-Dist: Django
